ragflow_mcp_server_aider/__init__.py
ragflow_mcp_server_aider/config.py
ragflow_mcp_server_aider/server.py
ragflow_mcp_server_aider-0.1.0.dist-info/WHEEL
ragflow_mcp_server_aider-0.1.0.dist-info/entry_points.txt
ragflow_mcp_server_aider-0.1.0.dist-info/METADATA
ragflow_mcp_server_aider-0.1.0.dist-info/RECORD
