Metadata-Version: 2.3
Name: ragflow-mcp-server-aider
Version: 0.1.0
Summary: RAGFlow MCP Server Aider
Requires-Dist: mcp>=1.18.0
Requires-Dist: ragflow-sdk>=0.21.0
Requires-Python: >=3.10
